odoo/addons/account_payment_order_lock_draft/README.rst
odoo/addons/account_payment_order_lock_draft/__init__.py
odoo/addons/account_payment_order_lock_draft/__manifest__.py
odoo/addons/account_payment_order_lock_draft/i18n/account_payment_order_lock_draft.pot
odoo/addons/account_payment_order_lock_draft/i18n/it.po
odoo/addons/account_payment_order_lock_draft/models/__init__.py
odoo/addons/account_payment_order_lock_draft/models/account_move.py
odoo/addons/account_payment_order_lock_draft/readme/CONTRIBUTORS.rst
odoo/addons/account_payment_order_lock_draft/readme/DESCRIPTION.rst
odoo/addons/account_payment_order_lock_draft/static/description/icon.png
odoo/addons/account_payment_order_lock_draft/static/description/index.html
odoo/addons/account_payment_order_lock_draft/tests/__init__.py
odoo/addons/account_payment_order_lock_draft/tests/test_account_payment_order_lock_draft.py
odoo14_addon_account_payment_order_lock_draft-14.0.1.0.1.dev6.dist-info/METADATA
odoo14_addon_account_payment_order_lock_draft-14.0.1.0.1.dev6.dist-info/WHEEL
odoo14_addon_account_payment_order_lock_draft-14.0.1.0.1.dev6.dist-info/top_level.txt
odoo14_addon_account_payment_order_lock_draft-14.0.1.0.1.dev6.dist-info/RECORD
